{
  "type": "minecraft:smithing_transform",
  "addition": {
    "item": "minecraft:netherite_ingot"
  },
  "base": {
    "item": "flintlock:halberd.diamond"
  },
  "result": {
    "item": "flintlock:halberd.netherite"
  },
  "template": {
    "item": "minecraft:netherite_upgrade_smithing_template"
  },
  "conditions": [
    {
      "type": "flintlock:config_conditional",
      "weapon": "halberd"
    }
  ],
  "fabric:load_conditions": [
    {
      "condition": "flintlock:config_conditional",
      "weapon": "halberd"
    }
  ]
}
